omxwaredev-0.0.0.39.dist-info/RECORD
omxwaredev-0.0.0.39.dist-info/metadata.json
omxwaredev-0.0.0.39.dist-info/WHEEL
omxwaredev-0.0.0.39.dist-info/entry_points.txt
omxwaredev-0.0.0.39.dist-info/DESCRIPTION.rst
omxwaredev-0.0.0.39.dist-info/top_level.txt
omxwaredev-0.0.0.39.dist-info/METADATA
omxware/KeycloakTest.py
omxware/omxware.py
omxware/ServiceException.py
omxware/Config.py
omxware/Domain.py
omxware/Connect.py
omxware/__init__.py
omxware/AESCipher.py
omxware/Protein.py
omxware/Genus.py
omxware/cli.py
omxware/omxware_old.py
omxware/Utils.py
omxware/DataException.py
omxware/Gene.py
omxware/Genome.py
omxware/ResultSet.py
