Metadata-Version: 2.0
Name: omxwaredev
Version: 0.0.0.39
Summary: OMXWare client
Home-page: https://github.com/c0mpiler/omxware
Author: Harsha Krishnareddy
Author-email: c0mpiler@outlook.com
License: UNKNOWN
Keywords: omxware
Platform: UNKNOWN
Classifier: Development Status :: 2 - Pre-Alpha
Classifier: Intended Audience :: Developers
Classifier: Natural Language :: English
Classifier: Programming Language :: Python :: 3.6
Requires-Dist: Click (>=6.0)
Requires-Dist: py-keycloak (>=0.0.1.4)
Requires-Dist: simplejson (>=3.16.0)
Requires-Dist: pprint
Requires-Dist: pandas
